setup.py
par_parallel/ProgressBar.py
par_parallel/__init__.py
par_parallel/parallel.py
par_parallel.egg-info/PKG-INFO
par_parallel.egg-info/SOURCES.txt
par_parallel.egg-info/dependency_links.txt
par_parallel.egg-info/not-zip-safe
par_parallel.egg-info/requires.txt
par_parallel.egg-info/top_level.txt