Metadata-Version: 1.1
Name: par-parallel
Version: 1.0
Summary: PAR: a PARallel and distributed job crusher
Home-page: https://github.com/UnixJunkie/PAR
Author: Francois Berenger
Author-email: berenger@riken.jp
License: GPL
Platform: UNKNOWN
Classifier: Development Status :: 6 - Mature
Classifier: Environment :: Console
Classifier: Intended Audience :: End Users/Desktop
Classifier: Intended Audience :: Science/Research
Classifier: Intended Audience :: System Administrators
Classifier: License :: OSI Approved :: GNU General Public License v3 or later (GPLv3+)
Classifier: Operating System :: POSIX
Classifier: Programming Language :: Python
